preprocessing/__init__.py
preprocessing/base.py
preprocessing/crossref.py
preprocessing/datacite.py
preprocessing/jalc.py
preprocessing/openaire.py
preprocessing/pubmed.py
preprocessing/datasource/__init__.py
preprocessing/datasource/config.ini
preprocessing/datasource/datasource.py
preprocessing/datasource/redis.py
preprocessing/finder/__init__.py
preprocessing/finder/nih.py
preprocessing/identifier_manager/__init__.py
preprocessing/identifier_manager/jid.py
preprocessing/identifier_manager/datasource/__init__.py
preprocessing/identifier_manager/datasource/datasource.py
preprocessing/identifier_manager/datasource/redis.py
oc_preprocessing-0.0.5.dist-info/LICENSE
oc_preprocessing-0.0.5.dist-info/METADATA
oc_preprocessing-0.0.5.dist-info/WHEEL
oc_preprocessing-0.0.5.dist-info/top_level.txt
oc_preprocessing-0.0.5.dist-info/RECORD
