Metadata-Version: 2.1
Name: oc-preprocessing
Version: 0.0.5
Summary: This package is meant to preprocess OpenCitations source dumps so to make them easily usable in OpenCitations main processes, by deleting unused information, splitting big files, and validating identifiers
Home-page: https://github.com/opencitations/preprocess
Author: OpenCitations authors
Author-email: OpenCitations authors <contact@opencitations.net>
License: BSD
Project-URL: Homepage, https://github.com/opencitations/preprocess
Project-URL: Bug Tracker, https://github.com/opencitations/preprocess/issues
Keywords: preprocessing data dumps
Classifier: Programming Language :: Python :: 3
Classifier: License :: OSI Approved :: ISC License (ISCL)
Classifier: Operating System :: OS Independent
Requires-Python: >=3.8
License-File: LICENSE
Requires-Dist: setuptools (>=61.0)
Requires-Dist: beautifulsoup4 (==4.12.2)
Requires-Dist: fakeredis (==2.10.3)
Requires-Dist: ndjson (==0.3.1)
Requires-Dist: oc-idmanager (==0.2.6)
Requires-Dist: pandas (==1.5.3)
Requires-Dist: requests (==2.28.2)
Requires-Dist: tqdm (==4.64.1)
Requires-Dist: zstandard (==0.19.0)
